kit_up/__init__.py
kit_up/py.typed
kit_up/core/__init__.py
kit_up/core/exceptions.py
kit_up/core/models.py
kit_up/core/settings.py
kit_up/core/utils.py
kit_up/core/values_objects.py
kit_up/core/applicators/__init__.py
kit_up/core/applicators/exceptions.py
kit_up/core/applicators/predicates.py
kit_up/core/clauses/__init__.py
kit_up/core/clauses/base.py
kit_up/core/clauses/exceptions.py
kit_up/core/clauses/predicates.py
kit_up/core/contexts/__init__.py
kit_up/core/contexts/base.py
kit_up/core/contexts/exceptions.py
kit_up/core/contexts/uow.py
kit_up/core/domains/__init__.py
kit_up/core/domains/base.py
kit_up/core/domains/crud.py
kit_up/core/domains/exceptions.py
kit_up/core/endpoints/__init__.py
kit_up/core/endpoints/rest.py
kit_up/core/mixins/__init__.py
kit_up/core/mixins/crud.py
kit_up/core/mixins/require.py
kit_up/core/repositories/__init__.py
kit_up/core/repositories/base.py
kit_up/core/repositories/crud.py
kit_up/core/repositories/exceptions.py
kit_up/core/repositories/exposable.py
kit_up/core/stashes/__init__.py
kit_up/core/stashes/base.py
kit_up/core/stashes/context_vars.py
kit_up/core/stashes/exceptions.py
kit_up/core/units_of_work/__init__.py
kit_up/core/units_of_work/base.py
kit_up/core/units_of_work/exceptions.py
kit_up/flavors/__init__.py
kit_up/flavors/filtering.py
kit_up/flavors/sql/__init__.py
kit_up/flavors/sql/dcl.py
kit_up/flavors/sql/ddl.py
kit_up/flavors/sql/dml.py
kit_up/flavors/sql/dql.py
kit_up/flavors/sql/tcl.py
kit_up/impl/__init__.py
kit_up/impl/falcon/__init__.py
kit_up/impl/falcon/crud.py
kit_up/impl/falcon/errors.py
kit_up/impl/mm/__init__.py
kit_up/impl/mm/conf.py
kit_up/impl/sql_alchemy/__init__.py
kit_up/impl/sql_alchemy/applicators.py
kit_up/impl/sql_alchemy/contexts.py
kit_up/impl/sql_alchemy/orm.py
kit_up/impl/sql_alchemy/repositories.py
kit_up/impl/sql_alchemy/require.py
kit_up/temp/__init__.py
kit_up/temp/fd_context.py
kit_up/temp/fd_repository.py
kit_up/temp/fd_uow.py
kit_up-0.0.6.dist-info/licenses/LICENSE
kit_up-0.0.6.dist-info/METADATA
kit_up-0.0.6.dist-info/WHEEL
kit_up-0.0.6.dist-info/top_level.txt
kit_up-0.0.6.dist-info/RECORD
