Metadata-Version: 2.4
Name: kit-up
Version: 0.0.6
Summary: Kit Up!
Author-email: Dima Burmistrov <pyctrl.dev@gmail.com>
License: Copyright (c) 2023-2024 Dmitry Burmistrov
Project-URL: Homepage, https://gitlab.com/pyctrl/kit-up
Project-URL: Bug Tracker, https://gitlab.com/pyctrl/kit-up/-/issues
Keywords: app,domain,model,repository,filter,structure,kit-up,kit_up
Classifier: Programming Language :: Python :: 3
Classifier: License :: OSI Approved :: MIT License
Classifier: Operating System :: OS Independent
Classifier: Development Status :: 4 - Beta
Classifier: Intended Audience :: Developers
Classifier: Topic :: Software Development :: Libraries :: Python Modules
Classifier: Typing :: Typed
Requires-Python: >=3.11
License-File: LICENSE
Requires-Dist: izulu>=0.10.2
Requires-Dist: miska
Requires-Dist: urnparse
Provides-Extra: sa
Requires-Dist: SQLAlchemy; extra == "sa"
Requires-Dist: sqlalchemy_mixins; extra == "sa"
Provides-Extra: falcon
Requires-Dist: falcon; extra == "falcon"
Provides-Extra: all
Requires-Dist: kit-up[sa]; extra == "all"
Requires-Dist: kit-up[falcon]; extra == "all"
Dynamic: license-file
